Workbook

Sheet Resumen
B2: Tracker de Contenido — Plataforma de Ingles (A1-B2)
B3: Roxy / Processa Digital Studio — actualizar celdas amarillas en la hoja 'Unidades'
B6: Nivel | C6: Grammar Explicacion — % Listo | D6: Vocab List — % Listo | E6: Reading — % Listo | F6: Listening — % Listo | G6: Writing Prompt — % Listo | H6: Unit Quiz — % Listo | I6: Total unidades
B7: A1 | C7: =COUNTIFS(Unidades!$A:$A,$B7,Unidades!H:H,"Listo")/COUNTIF(Unidades!$A:$A,$B7) -> 0 | D7: =COUNTIFS(Unidades!$A:$A,$B7,Unidades!I:I,"Listo")/COUNTIF(Unidades!$A:$A,$B7) -> 0 | E7: =COUNTIFS(Unidades!$A:$A,$B7,Unidades!J:J,"Listo")/COUNTIF(Unidades!$A:$A,$B7) -> 0 | F7: =COUNTIFS(Unidades!$A:$A,$B7,Unidades!K:K,"Listo")/COUNTIF(Unidades!$A:$A,$B7) -> 0 | G7: =COUNTIFS(Unidades!$A:$A,$B7,Unidades!L:L,"Listo")/COUNTIF(Unidades!$A:$A,$B7) -> 0 | H7: =COUNTIFS(Unidades!$A:$A,$B7,Unidades!M:M,"Listo")/COUNTIF(Unidades!$A:$A,$B7) -> 0 | I7: =COUNTIF(Unidades!$A:$A,$B7) -> 16
B8: A2 | C8: =COUNTIFS(Unidades!$A:$A,$B8,Unidades!H:H,"Listo")/COUNTIF(Unidades!$A:$A,$B8) -> 0 | D8: =COUNTIFS(Unidades!$A:$A,$B8,Unidades!I:I,"Listo")/COUNTIF(Unidades!$A:$A,$B8) -> 0 | E8: =COUNTIFS(Unidades!$A:$A,$B8,Unidades!J:J,"Listo")/COUNTIF(Unidades!$A:$A,$B8) -> 0 | F8: =COUNTIFS(Unidades!$A:$A,$B8,Unidades!K:K,"Listo")/COUNTIF(Unidades!$A:$A,$B8) -> 0 | G8: =COUNTIFS(Unidades!$A:$A,$B8,Unidades!L:L,"Listo")/COUNTIF(Unidades!$A:$A,$B8) -> 0 | H8: =COUNTIFS(Unidades!$A:$A,$B8,Unidades!M:M,"Listo")/COUNTIF(Unidades!$A:$A,$B8) -> 0 | I8: =COUNTIF(Unidades!$A:$A,$B8) -> 16
B9: B1.1 | C9: =COUNTIFS(Unidades!$A:$A,$B9,Unidades!H:H,"Listo")/COUNTIF(Unidades!$A:$A,$B9) -> 0 | D9: =COUNTIFS(Unidades!$A:$A,$B9,Unidades!I:I,"Listo")/COUNTIF(Unidades!$A:$A,$B9) -> 0 | E9: =COUNTIFS(Unidades!$A:$A,$B9,Unidades!J:J,"Listo")/COUNTIF(Unidades!$A:$A,$B9) -> 0 | F9: =COUNTIFS(Unidades!$A:$A,$B9,Unidades!K:K,"Listo")/COUNTIF(Unidades!$A:$A,$B9) -> 0 | G9: =COUNTIFS(Unidades!$A:$A,$B9,Unidades!L:L,"Listo")/COUNTIF(Unidades!$A:$A,$B9) -> 0 | H9: =COUNTIFS(Unidades!$A:$A,$B9,Unidades!M:M,"Listo")/COUNTIF(Unidades!$A:$A,$B9) -> 0 | I9: =COUNTIF(Unidades!$A:$A,$B9) -> 8
B10: B1.2 | C10: =COUNTIFS(Unidades!$A:$A,$B10,Unidades!H:H,"Listo")/COUNTIF(Unidades!$A:$A,$B10) -> 0 | D10: =COUNTIFS(Unidades!$A:$A,$B10,Unidades!I:I,"Listo")/COUNTIF(Unidades!$A:$A,$B10) -> 0 | E10: =COUNTIFS(Unidades!$A:$A,$B10,Unidades!J:J,"Listo")/COUNTIF(Unidades!$A:$A,$B10) -> 0 | F10: =COUNTIFS(Unidades!$A:$A,$B10,Unidades!K:K,"Listo")/COUNTIF(Unidades!$A:$A,$B10) -> 0 | G10: =COUNTIFS(Unidades!$A:$A,$B10,Unidades!L:L,"Listo")/COUNTIF(Unidades!$A:$A,$B10) -> 0 | H10: =COUNTIFS(Unidades!$A:$A,$B10,Unidades!M:M,"Listo")/COUNTIF(Unidades!$A:$A,$B10) -> 0 | I10: =COUNTIF(Unidades!$A:$A,$B10) -> 8
B11: B2 | C11: =COUNTIFS(Unidades!$A:$A,$B11,Unidades!H:H,"Listo")/COUNTIF(Unidades!$A:$A,$B11) -> 0 | D11: =COUNTIFS(Unidades!$A:$A,$B11,Unidades!I:I,"Listo")/COUNTIF(Unidades!$A:$A,$B11) -> 0 | E11: =COUNTIFS(Unidades!$A:$A,$B11,Unidades!J:J,"Listo")/COUNTIF(Unidades!$A:$A,$B11) -> 0 | F11: =COUNTIFS(Unidades!$A:$A,$B11,Unidades!K:K,"Listo")/COUNTIF(Unidades!$A:$A,$B11) -> 0 | G11: =COUNTIFS(Unidades!$A:$A,$B11,Unidades!L:L,"Listo")/COUNTIF(Unidades!$A:$A,$B11) -> 0 | H11: =COUNTIFS(Unidades!$A:$A,$B11,Unidades!M:M,"Listo")/COUNTIF(Unidades!$A:$A,$B11) -> 0 | I11: =COUNTIF(Unidades!$A:$A,$B11) -> 16
B12: TOTAL | C12: =COUNTIF(Unidades!H:H,"Listo")/COUNTA(Unidades!H2:H65) -> 0 | D12: =COUNTIF(Unidades!I:I,"Listo")/COUNTA(Unidades!I2:I65) -> 0 | E12: =COUNTIF(Unidades!J:J,"Listo")/COUNTA(Unidades!J2:J65) -> 0 | F12: =COUNTIF(Unidades!K:K,"Listo")/COUNTA(Unidades!K2:K65) -> 0 | G12: =COUNTIF(Unidades!L:L,"Listo")/COUNTA(Unidades!L2:L65) -> 0 | H12: =COUNTIF(Unidades!M:M,"Listo")/COUNTA(Unidades!M2:M65) -> 0 | I12: =COUNTA(Unidades!A2:A65) -> 64
B15: Como usar esta hoja:
B16: 1. Ve a la hoja 'Unidades' y llena la columna 'Preguntas del banco (550)' con cuantas preguntas ya tienes por unidad.
B17: 2. Cambia cada columna de estado (Grammar, Vocab, Reading, Listening, Writing, Quiz) a Pendiente / En progreso / Listo usando el menu desplegable.
B18: 3. Esta hoja se actualiza sola con el % de avance por nivel y tipo de contenido.
B19: 4. La columna 'Notas' es libre — usala para anotar fuente del contenido, quien lo esta escribiendo, o pendientes.
B27: Alcance del piloto (MVP): 20 unidades x 6 lecciones = 120 lecciones
B28: A1: unidades 1-5 · A2: unidades 1-5 · B1: unidades 1-5 de B1.1 · B2: unidades 1-5 — el resto queda en Fase 2

Sheet Especificaciones_Contenido
B2: Especificacion de contenido por unidad (la 'receta' que sigue cada unidad)
B3: Usar esta hoja como brief para quien escriba el contenido de cada unidad — mantiene todo uniforme.
B5: Elemento | C5: A1 / A2 | D5: B1.1 / B1.2 | E5: B2 | F5: Notas
B6: Explicacion gramatical | C6: 150-250 palabras. 1 regla central + 3-4 ejemplos + 1 error comun. | D6: 250-350 palabras. Regla central + 1-2 sub-reglas + 4-5 ejemplos + errores comunes. | E6: 300-450 palabras. Incluir matices, excepciones y diferencias de registro (formal/informal). | F6: Escribir SIEMPRE con el can-do statement de la unidad como objetivo, no solo la regla en abstracto.
B7: Lista de vocabulario | C7: 10-12 palabras/frases. | D7: 15-18 palabras/frases. | E7: 18-22 palabras/frases. | F7: Cada palabra con: definicion simple, ejemplo en oracion, y (fase 2) audio de pronunciacion.
B8: Reading passage | C8: 80-120 palabras (A1) / 120-180 (A2). 4-5 preguntas de comprension. | D8: 180-280 palabras. 5-6 preguntas de comprension. | E8: 280-400 palabras. 6 preguntas de comprension, incluir inferencia/opinion. | F8: Debe usar el vocabulario Y la gramatica de la unidad — no un texto generico del nivel.
B9: Listening script | C9: 60-100 palabras / 30-45 seg (A1) / 100-150 palabras / 45-60 seg (A2). 4-5 preguntas. | D9: 150-220 palabras / 1-1.5 min. 5-6 preguntas. | E9: 220-320 palabras / 1.5-2.5 min. 6 preguntas, incluir inferencia. | F9: Escribir el script primero: sirve tanto para grabacion real como para TTS mientras llegan los audios.
B10: Writing prompt + rubrica | C10: A1: 3-5 oraciones. A2: parrafo corto (40-60 palabras). | D10: 80-120 palabras. | E10: 120-180 palabras. | F10: Rubrica de 4 criterios: cumplimiento de la tarea, uso del punto gramatical de la unidad, vocabulario, coherencia.
B11: Quiz de unidad | C11: 10-12 items. Mezcla: seleccion multiple, fill-in-blank, verdadero/falso. | D11: 10-12 items. Agregar emparejar y ordenar oraciones. | E11: 10-12 items. Agregar encontrar-el-error para gramatica avanzada. | F11: ~60% gramatica de la unidad / 40% vocabulario. Reusar preguntas del banco de 550 que clasificaron 'Alta' o 'Media' como bono.

Sheet Unidades
A1: Nivel | B1: Unidad # | C1: Titulo | D1: Tema gramatical | E1: Vocabulario / tema lexico | F1: Funcion comunicativa | G1: Preguntas del banco (550) | H1: Grammar Explicacion | I1: Vocab List | J1: Reading | K1: Listening | L1: Writing Prompt | M1: Unit Quiz | N1: Notas | O1: Fase
A2: A1 | B2: 1 | C2: Nice to Meet You! | D2: Verb to be: afirmativo, negativo y preguntas | E2: Saludos, presentaciones, informacion personal | F2: Puede saludar, presentarse, decir quien es y de donde es | G2: =COUNTIF(Banco_Clasificado!$G:$G,$C2) -> 1 | H2: Pendiente | I2: Pendiente | J2: Pendiente | K2: Pendiente | L2: Pendiente | M2: Pendiente | O2: Fase 1 (MVP)
A3: A1 | B3: 2 | C3: Transportation | D3: Subject, object y possessive pronouns | E3: Transporte y desplazamientos | F3: Puede hablar de personas y objetos y desenvolverse en transporte | G3: =COUNTIF(Banco_Clasificado!$G:$G,$C3) -> 0 | H3: Pendiente | I3: Pendiente | J3: Pendiente | K3: Pendiente | L3: Pendiente | M3: Pendiente | O3: Fase 1 (MVP)
A4: A1 | B4: 3 | C4: Restaurants | D4: Singular/plural nouns; there is/there are; articulos | E4: Restaurantes, comida, biblioteca/estudios | F4: Puede describir lo que hay en un lugar y hablar de comida/restaurantes | G4: =COUNTIF(Banco_Clasificado!$G:$G,$C4) -> 0 | H4: Pendiente | I4: Pendiente | J4: Pendiente | K4: Pendiente | L4: Pendiente | M4: Pendiente | O4: Fase 1 (MVP)
A5: A1 | B5: 4 | C5: Crime | D5: Be: short answers; this/that/these/those | E5: Crimen, policia, situaciones legales basicas | F5: Puede responder preguntas simples, identificar objetos y hablar de situaciones de delitos | G5: =COUNTIF(Banco_Clasificado!$G:$G,$C5) -> 0 | H5: Pendiente | I5: Pendiente | J5: Pendiente | K5: Pendiente | L5: Pendiente | M5: Pendiente | O5: Fase 1 (MVP)
A6: A1 | B6: 5 | C6: Art | D6: Verb to be: afirmativo, Yes/No questions y contractions | E6: Arte, musica, entretenimiento | F6: Puede describir personas/situaciones sencillas y hablar de entretenimiento | G6: =COUNTIF(Banco_Clasificado!$G:$G,$C6) -> 1 | H6: Pendiente | I6: Pendiente | J6: Pendiente | K6: Pendiente | L6: Pendiente | M6: Pendiente | O6: Fase 1 (MVP)
A7: A1 | B7: 6 | C7: Occupations | D7: Present Simple para ocupaciones | E7: Profesiones, trabajos, estudios | F7: Puede decir que hace, donde trabaja/estudia y hablar de ocupaciones | G7: =COUNTIF(Banco_Clasificado!$G:$G,$C7) -> 0 | H7: Pendiente | I7: Pendiente | J7: Pendiente | K7: Pendiente | L7: Pendiente | M7: Pendiente | O7: Fase 2
A8: A1 | B8: 7 | C8: Homes and Families | D8: Present Simple; have para posesion; posesivos | E8: Casa, vivienda, familia | F8: Puede describir su casa y hablar de su familia | G8: =COUNTIF(Banco_Clasificado!$G:$G,$C8) -> 2 | H8: Pendiente | I8: Pendiente | J8: Pendiente | K8: Pendiente | L8: Pendiente | M8: Pendiente | O8: Fase 2
A9: A1 | B9: 8 | C9: Food and Drink | D9: Count/non-count nouns; have/has; would like/want | E9: Comida y bebidas, restaurante | F9: Puede hablar de lo que come y bebe y pedir comida | G9: =COUNTIF(Banco_Clasificado!$G:$G,$C9) -> 3 | H9: Pendiente | I9: Pendiente | J9: Pendiente | K9: Pendiente | L9: Pendiente | M9: Pendiente | O9: Fase 2
A10: A1 | B10: 9 | C10: Health and Fitness | D10: Imperatives | E10: Salud, ejercicio, fitness | F10: Puede dar y seguir comandos, instrucciones, solicitudes y sugerencias | G10: =COUNTIF(Banco_Clasificado!$G:$G,$C10) -> 2 | H10: Pendiente | I10: Pendiente | J10: Pendiente | K10: Pendiente | L10: Pendiente | M10: Pendiente | O10: Fase 2
A11: A1 | B11: 10 | C11: Business | D11: Present Progressive: afirmativo, preguntas, short answers y negativo/Wh | E11: Negocios, hoteles, viajes de negocios | F11: Puede decir que esta sucediendo y hablar de situaciones actuales | G11: =COUNTIF(Banco_Clasificado!$G:$G,$C11) -> 0 | H11: Pendiente | I11: Pendiente | J11: Pendiente | K11: Pendiente | L11: Pendiente | M11: Pendiente | O11: Fase 2
A12: A1 | B12: 11 | C12: Shopping | D12: Possessive nouns; Present Progressive; contractions y spelling changes | E12: Compras, objetos, verbos, adjetivos | F12: Puede hablar de productos, pertenencias y acciones en progreso | G12: =COUNTIF(Banco_Clasificado!$G:$G,$C12) -> 1 | H12: Pendiente | I12: Pendiente | J12: Pendiente | K12: Pendiente | L12: Pendiente | M12: Pendiente | O12: Fase 2
A13: A1 | B13: 12 | C13: Free Time | D13: Likes/dislikes; Present Simple, Present Progressive y be going to para futuro | E13: Tiempo libre, deportes, actividades | F13: Puede expresar gustos, hablar de tiempo libre y hacer planes | G13: =COUNTIF(Banco_Clasificado!$G:$G,$C13) -> 26 | H13: Pendiente | I13: Pendiente | J13: Pendiente | K13: Pendiente | L13: Pendiente | M13: Pendiente | O13: Fase 2
... A65: B2 | B65: 16 | C65: Architecture | D65: Simple tenses: review | E65: Arquitectura, diseno, construccion, proyectos | F65: Puede describir proyectos, hablar de arquitectura y discutir decisiones y preferencias profesionales — cierre de nivel | G65: =COUNTIF(Banco_Clasificado!$G:$G,$C65) -> 0 | H65: Pendiente | I65: Pendiente | J65: Pendiente | K65: Pendiente | L65: Pendiente | M65: Pendiente | O65: Fase 2

Sheet Banco_Clasificado
A1: ID pregunta | B1: Nivel | C1: Destreza | D1: Tipo | E1: Tema/Titulo (Reading-Listening) | F1: Unidad sugerida # | G1: Unidad sugerida - nombre | H1: Confianza | I1: Vista previa | J1: Revisado por profesor?
A2: UoL-A1-C01 | B2: A1 | C2: Language Use | D2: multichoice | G2: SIN CLASIFICAR | H2: Sin coincidencia | I2: Context The university timetable includes a 90-minute break in the middle of every teaching day. Students usually _____ lunch together in th
A3: UoL-A1-C02 | B3: A1 | C3: Language Use | D3: multichoice | F3: 7 | G3: Homes and Families | H3: Baja (revisar) | I3: Context The last lecture of the day finishes at five o'clock in the afternoon. After their final class, most students _____ home to eat dinn
A4: UoL-A1-C03 | B4: A1 | C4: Language Use | D4: multichoice | G4: SIN CLASIFICAR | H4: Sin coincidencia | I4: Context The university sports facilities are available to all students every afternoon and at weekends. Many students _____ a sport there af
A5: UoL-A1-C04 | B5: A1 | C5: Language Use | D5: multichoice | F5: 9 | G5: Health and Fitness | H5: Baja (revisar) | I5: Context The student health centre encourages all students to maintain an active and balanced lifestyle. The doctor recommends that students
A6: UoL-A1-C05 | B6: A1 | C6: Language Use | D6: multichoice | F6: 12 | G6: Free Time | H6: Baja (revisar) | I6: Context After a long and tiring week of exams, students need some time to relax and switch off. Many students _____ a film at the cinema or
A7: UoL-A1-C06 | B7: A1 | C7: Language Use | D7: multichoice | G7: SIN CLASIFICAR | H7: Sin coincidencia | I7: Context The student forgot her textbook at home. It was an important day. She decided to _____ a message to her classmate to ask if she coul
A8: UoL-A1-C07 | B8: A1 | C8: Language Use | D8: multichoice | G8: SIN CLASIFICAR | H8: Sin coincidencia | I8: Context It was the first day of term and many new students were trying to find their classrooms. Several students _____ their way in the lar
A9: UoL-A1-C08 | B9: A1 | C9: Language Use | D9: multichoice | G9: SIN CLASIFICAR | H9: Sin coincidencia | I9: Context The university is located several kilometres from the city centre where many students live. Every morning, Juliana _____ an early bu
A10: UoL-A1-C09 | B10: A1 | C10: Language Use | D10: multichoice | G10: SIN CLASIFICAR | H10: Sin coincidencia | I10: Context Meeting new people can feel uncomfortable at first, especially in an unfamiliar environment. During orientation week, Diego found it
A11: UoL-A1-C10 | B11: A1 | C11: Language Use | D11: multichoice | F11: 7 | G11: Homes and Families | H11: Baja (revisar) | I11: Context University students need to balance their studies with other important areas of their lives. Most students _____ time with their fri
A12: UoL-A1-C11 | B12: A1 | C12: Language Use | D12: multichoice | G12: SIN CLASIFICAR | H12: Sin coincidencia | I12: Context Students who travel by public transport need to bring their study materials with them every day. Most students _____ a backpack to u
A13: UoL-A1-C12 | B13: A1 | C13: Language Use | D13: multichoice | F13: 12 | G13: Free Time | H13: Baja (revisar) | I13: Context The professor encouraged all students to participate actively during lectures. "Don't be shy," she said. "Feel free to _____ a quest
A14: UoL-A1-G01 | B14: A1 | C14: Language Use | D14: multichoice | G14: SIN CLASIFICAR | H14: Sin coincidencia | I14: Context My name is Valentina. I study at a university in the city and I love my programme. I _____ eighteen years old and I live with my fam
A15: UoL-A1-G02 | B15: A1 | C15: Language Use | D15: multichoice | G15: SIN CLASIFICAR | H15: Sin coincidencia | I15: Context Daniel is studying in his first year at university. He works very hard and attends every class. His favourite professor _____ very p
A16: UoL-A1-G03 | B16: A1 | C16: Language Use | D16: multichoice | G16: SIN CLASIFICAR | H16: Sin coincidencia | I16: Context María and I met during the first week of the academic year and we became very good friends. We _____ classmates in the same programm
A17: UoL-A1-G04 | B17: A1 | C17: Language Use | D17: multichoice | G17: SIN CLASIFICAR | H17: Sin coincidencia | I17: Context A new student arrives at the faculty building. She looks lost and is searching for her classroom. "_____ you in the first-year group
A18: UoL-A1-G05 | B18: A1 | C18: Language Use | D18: multichoice | F18: 12 | G18: Free Time | H18: Baja (revisar) | I18: Context Carlos has a brother called Andrés who lives and works in another city. Andrés _____ a student anymore. He already graduated several
A19: UoL-A1-G06 | B19: A1 | C19: Language Use | D19: multichoice | F19: 11 | G19: Shopping | H19: Baja (revisar) | I19: Context It is the beginning of a new semester. Yesterday, Sofia went shopping for all her university materials. I _____ a new laptop, three
A20: UoL-A1-G07 | B20: A1 | C20: Language Use | D20: multichoice | G20: SIN CLASIFICAR | H20: Sin coincidencia | I20: Context The librarian is helping a new student register for the borrowing service at the front desk. "_____ she got a valid student card wit
A21: UoL-A1-G08 | B21: A1 | C21: Language Use | D21: multichoice | F21: 15 | G21: Computers and Phones | H21: Alta (respuesta clave) | I21: Context Laura is applying for a customer service position at an international company in the city centre. She _____ speak English and French
A22: UoL-A1-G09 | B22: A1 | C22: Language Use | D22: multichoice | G22: SIN CLASIFICAR | H22: Sin coincidencia | I22: Context The university cafeteria is the most popular place for students to eat between their morning classes. It _____ hot meals, sandwiches
A23: UoL-A1-G10 | B23: A1 | C23: Language Use | D23: multichoice | F23: 1 | G23: Nice to Meet You! | H23: Baja (revisar) | I23: Context Pedro follows a strict vegetarian diet for personal health and ethical reasons. He _____ meat, fish, or poultry of any kind. He only
A24: UoL-A1-G11 | B24: A1 | C24: Language Use | D24: multichoice | F24: 12 | G24: Free Time | H24: Baja (revisar) | I24: Context Luisa is looking for a comfortable place to study that is close to where she lives. Luckily, _____ a quiet café on the corner of her
A25: UoL-A1-G12 | B25: A1 | C25: Language Use | D25: multichoice | G25: SIN CLASIFICAR | H25: Sin coincidencia | I25: Context The new faculty building opened last year and students are very pleased with the modern facilities. _____ three computer labs, a lar
A26: UoL-A1-G13 | B26: A1 | C26: Language Use | D26: multichoice | G26: SIN CLASIFICAR | H26: Sin coincidencia | I26: Context Natalia received some very exciting news this morning. A company offered her a new job. It is _____ internship at a technology compa
A27: UoL-A1-G14 | B27: A1 | C27: Language Use | D27: multichoice | G27: SIN CLASIFICAR | H27: Sin coincidencia | I27: Context The English professor is well-known across the faculty for her innovative and engaging approach. _____ uses videos, games, and real
A28: UoL-A1-G15 | B28: A1 | C28: Language Use | D28: multichoice | G28: SIN CLASIFICAR | H28: Sin coincidencia | I28: Context There is an important sign at the entrance of the university examination hall. The sign clearly states: "_____ electronic devices of
A29: UoL-A1-P01 | B29: A1 | C29: Language Use | D29: multichoice | G29: SIN CLASIFICAR | H29: Sin coincidencia | I29: Context The first lesson of each day begins very early. Punctuality is essential for all students. All morning classes start _____ eight o'c
A30: UoL-A1-P02 | B30: A1 | C30: Language Use | D30: multichoice | G30: SIN CLASIFICAR | H30: Sin coincidencia | I30: Context The faculty organises extra study sessions throughout the week to help students prepare for exams. The voluntary English conversatio
A31: UoL-A1-P03 | B31: A1 | C31: Language Use | D31: multichoice | G31: SIN CLASIFICAR | H31: Sin coincidencia | I31: Context The university calendar divides the year into two distinct teaching periods separated by holidays. The second semester begins _____
A32: UoL-A1-P04 | B32: A1 | C32: Language Use | D32: multichoice | G32: SIN CLASIFICAR | H32: Sin coincidencia | I32: Context The professor is telling students about next week's practical session. "Our next class will be _____ the computer laboratory on the
A33: UoL-A1-P05 | B33: A1 | C33: Language Use | D33: multichoice | G33: SIN CLASIFICAR | H33: Sin coincidencia | I33: Context A student cannot find an important document that he needs for his afternoon appointment. "Your student card is _____ the desk, next
A34: UoL-A1-P06 | B34: A1 | C34: Language Use | D34: multichoice | F34: 9 | G34: Health and Fitness | H34: Baja (revisar) | I34: Context The university has recently opened a modern new health and wellness centre for all students. The new centre is located _____ the spo
A35: UoL-A1-P07 | B35: A1 | C35: Language Use | D35: multichoice | G35: SIN CLASIFICAR | H35: Sin coincidencia | I35: Context The graduation ceremony takes place outdoors in the university gardens every December. The graduating students stand _____ the main
A36: UoL-A1-P08 | B36: A1 | C36: Language Use | D36: multichoice | G36: SIN CLASIFICAR | H36: Sin coincidencia | I36: Context The student break room is a small space where staff and students can relax during the day. It is located _____ the main library and
A37: UoL-A1-P09 | B37: A1 | C37: Language Use | D37: multichoice | G37: SIN CLASIFICAR | H37: Sin coincidencia | I37: Context During the examination period, students choose different environments that suit their study style. Valentina always prefers to study
A38: UoL-A1-P10 | B38: A1 | C38: Language Use | D38: multichoice | G38: SIN CLASIFICAR | H38: Sin coincidencia | I38: Context The student could not see the information on the board because someone tall was sitting near her. A student who was very tall was si
A39: UoL-A1-V01 | B39: A1 | C39: Language Use | D39: multichoice | G39: SIN CLASIFICAR | H39: Sin coincidencia | I39: Context Catalina has a very strong and loving relationship with all the members of her extended family. Her mother's mother is her _____. Sh
A40: UoL-A1-V02 | B40: A1 | C40: Language Use | D40: multichoice | G40: SIN CLASIFICAR | H40: Sin coincidencia | I40: Context Simón has always dreamed of helping sick people and saving lives in his community. After many years of university study, he became a
A41: UoL-A1-V03 | B41: A1 | C41: Language Use | D41: multichoice | G41: SIN CLASIFICAR | H41: Sin coincidencia | I41: Context David needs to find several academic books and articles for an important assignment. He goes to the university _____ every afternoon
A42: UoL-A1-V04 | B42: A1 | C42: Language Use | D42: multichoice | F42: 15 | G42: Computers and Phones | H42: Baja (revisar) | I42: Context The reading room has strict rules to help everyone concentrate and work effectively. It is always very _____ inside. Students are no
A43: UoL-A1-V05 | B43: A1 | C43: Language Use | D43: multichoice | F43: 14 | G43: Weather | H43: Baja (revisar) | I43: Context The climate in this city changes dramatically between the summer and winter months. In December and January, the weather becomes ver
A44: UoL-A1-V06 | B44: A1 | C44: Language Use | D44: multichoice | G44: SIN CLASIFICAR | H44: Sin coincidencia | I44: Context The main lecture hall is used for the biggest classes and all official university events. It is an extremely _____ room. More than t
A45: UoL-A1-V07 | B45: A1 | C45: Language Use | D45: multichoice | G45: SIN CLASIFICAR | H45: Sin coincidencia | I45: Context Ana has a very organised daily schedule during the academic semester. She has all her classes in the _____, so she can use the after
A46: UoL-A1-V08 | B46: A1 | C46: Language Use | D46: multichoice | G46: SIN CLASIFICAR | H46: Sin coincidencia | I46: Context After the accident on the sports field, the injured student needed urgent medical attention. An ambulance was called and took him to
A47: UoL-A1-V09 | B47: A1 | C47: Language Use | D47: multichoice | G47: SIN CLASIFICAR | H47: Sin coincidencia | I47: Context The week of final examinations is by far the most demanding period of the academic year. By Thursday evening, most students feel com
A48: UoL-A1-V10 | B48: A1 | C48: Language Use | D48: multichoice | G48: SIN CLASIFICAR | H48: Sin coincidencia | I48: Context The academic year at the university is divided into two separate study periods. The _____ semester runs from January to June, and th
A49: UoL-A1-V11 | B49: A1 | C49: Language Use | D49: multichoice | G49: SIN CLASIFICAR | H49: Sin coincidencia | I49: Context The university offers many additional services to help students during their studies. English conversation sessions are completely _
A50: UoL-A1-V12 | B50: A1 | C50: Language Use | D50: multichoice | G50: SIN CLASIFICAR | H50: Sin coincidencia | I50: Context Students need to know where their lessons take place before the semester begins. All practical sessions take place in a different __
A51: UoL-A1-V13 | B51: A1 | C51: Language Use | D51: multichoice | F51: 12 | G51: Free Time | H51: Baja (revisar) | I51: Context The first year of university is a significant change from secondary school for most students. Many first-year students find the tran
A52: UoL-A2-C01 | B52: A2 | C52: Language Use | D52: multichoice | G52: SIN CLASIFICAR | H52: Sin coincidencia | I52: Context The professor reminded students about the strict regulations for academic work at the end of class. "You must _____ your assignments
A53: UoL-A2-C02 | B53: A2 | C53: Language Use | D53: multichoice | F53: 16 | G53: Knowing a Second Language | H53: Baja (revisar) | I53: Context Students must demonstrate a minimum level of English before being permitted to advance to the next year. Those who _____ the languag
A54: UoL-A2-C03 | B54: A2 | C54: Language Use | D54: multichoice | G54: SIN CLASIFICAR | H54: Sin coincidencia | I54: Context The professor operates a strict attendance policy across all her courses this academic year. Students who _____ more than three sess
A55: UoL-A2-C04 | B55: A2 | C55: Language Use | D55: multichoice | G55: SIN CLASIFICAR | H55: Sin coincidencia | I55: Context The student association planned an outdoor event, but it had to be cancelled unexpectedly. There was _____ rain all morning and the
A56: UoL-A2-C05 | B56: A2 | C56: Language Use | D56: multichoice | G56: SIN CLASIFICAR | H56: Sin coincidencia | I56: Context The communications module requires students to demonstrate their ability to speak formally in English. Each student must _____ a ten
A57: UoL-A2-C06 | B57: A2 | C57: Language Use | D57: multichoice | G57: SIN CLASIFICAR | H57: Sin coincidencia | I57: Context Many students work part-time jobs in the evenings and at weekends to support their studies. Tomás works at a local restaurant every
A58: UoL-A2-C07 | B58: A2 | C58: Language Use | D58: multichoice | G58: SIN CLASIFICAR | H58: Sin coincidencia | I58: Context University life involves many costs that students need to manage carefully on a tight budget. Most students _____ a significant amou
A59: UoL-A2-C08 | B59: A2 | C59: Language Use | D59: multichoice | F59: 13 | G59: Saving Energy | H59: Baja (revisar) | I59: Context The faculty holds an annual competition to celebrate innovation and creativity among students. The engineering team was delighted to
A60: UoL-A2-C09 | B60: A2 | C60: Language Use | D60: multichoice | F60: 3 | G60: Interesting People | H60: Baja (revisar) | I60: Context Extracurricular activities are an excellent way to develop skills and meet new people at university. Many students _____ a sports cl
A61: UoL-A2-C10 | B61: A2 | C61: Language Use | D61: multichoice | G61: SIN CLASIFICAR | H61: Sin coincidencia | I61: Context The examination regulations are explained clearly to all students at the start of every academic year. Any student who _____ a rule
A62: UoL-A2-C11 | B62: A2 | C62: Language Use | D62: multichoice | G62: SIN CLASIFICAR | H62: Sin coincidencia | I62: Context The professor told students about a famous professional who overcame many obstacles. He explained that she worked extremely hard to
A63: UoL-A2-C12 | B63: A2 | C63: Language Use | D63: multichoice | G63: SIN CLASIFICAR | H63: Sin coincidencia | I63: Context The university runs a range of free workshops designed to support students throughout their studies. Students are strongly encourage
A64: UoL-A2-G01 | B64: A2 | C64: Language Use | D64: multichoice | G64: SIN CLASIFICAR | H64: Sin coincidencia | I64: Context Last semester was an extremely demanding period for all the students in the programme. Sofia _____ the library every single evening
A65: UoL-A2-G02 | B65: A2 | C65: Language Use | D65: multichoice | G65: SIN CLASIFICAR | H65: Sin coincidencia | I65: Context The annual field trip to a nearby industrial facility was a highlight of the academic calendar. The journey _____ approximately two
A66: UoL-A2-G03 | B66: A2 | C66: Language Use | D66: multichoice | G66: SIN CLASIFICAR | H66: Sin coincidencia | I66: Context Andrea needed to purchase several items before starting her laboratory course this term. She _____ a scientific calculator, safety g
A67: UoL-A2-G04 | B67: A2 | C67: Language Use | D67: multichoice | G67: SIN CLASIFICAR | H67: Sin coincidencia | I67: Context The group of students was looking forward to the excursion for several weeks. Unfortunately, they _____ because the coach broke down
A68: UoL-A2-G05 | B68: A2 | C68: Language Use | D68: multichoice | G68: SIN CLASIFICAR | H68: Sin coincidencia | I68: Context A student receives an urgent phone call from her flatmate while she is at the library. "I can't talk right now. I _____ an important
A69: UoL-A2-G06 | B69: A2 | C69: Language Use | D69: multichoice | F69: 12 | G69: Traveling Abroad | H69: Alta (respuesta clave) | I69: Context After finishing her degree, Valentina has very clear and specific plans for her professional future. She _____ apply for a postgradu
A70: UoL-A2-G07 | B70: A2 | C70: Language Use | D70: multichoice | F70: 12 | G70: Traveling Abroad | H70: Alta (respuesta clave) | I70: Context The professor is delivering a lecture about how technology is shaping the future of many professions. "Artificial intelligence _____
A71: UoL-A2-G08 | B71: A2 | C71: Language Use | D71: multichoice | G71: SIN CLASIFICAR | H71: Sin coincidencia | I71: Context The recently renovated campus library has much better resources than the previous building. It is _____ than the old one and gives s
A72: UoL-A2-G09 | B72: A2 | C72: Language Use | D72: multichoice | G72: SIN CLASIFICAR | H72: Sin coincidencia | I72: Context The university has received several national awards for academic excellence over recent years. Last year, independent reviewers offi
A73: UoL-A2-G10 | B73: A2 | C73: Language Use | D73: multichoice | F73: 8 | G73: Getting Help | H73: Baja (revisar) | I73: Context The first-year students were finding the academic writing requirements very challenging. The professor decided to create additional
A74: UoL-A2-G11 | B74: A2 | C74: Language Use | D74: multichoice | G74: SIN CLASIFICAR | H74: Sin coincidencia | I74: Context Marcela is widely regarded as one of the most punctual and dedicated students in the programme. She _____ arrives late to any class.
A75: UoL-A2-G12 | B75: A2 | C75: Language Use | D75: multichoice | F75: 9 | G75: A Bad Day | H75: Alta (respuesta clave) | I75: Context Students who participate in clinical placements must adhere to a strict professional code of conduct. They _____ wear their full uni
A76: UoL-A2-G13 | B76: A2 | C76: Language Use | D76: multichoice | G76: SIN CLASIFICAR | H76: Sin coincidencia | I76: Context The annual graduation ceremony was a deeply moving and memorable event for all those who attended. All the families in the audience
A77: UoL-A2-G14 | B77: A2 | C77: Language Use | D77: multichoice | F77: 12 | G77: Traveling Abroad | H77: Alta (respuesta clave) | I77: Context A classmate is feeling overwhelmed by the amount of work she has before the submission deadline. "Don't stress about it," says Diego
A78: UoL-A2-G15 | B78: A2 | C78: Language Use | D78: multichoice | F78: 12 | G78: Traveling Abroad | H78: Alta (respuesta clave) | I78: Context Dark clouds are rapidly filling the sky above the sports field where students are training. "Look at those clouds --- it _____ pour
A79: UoL-A2-P01 | B79: A2 | C79: Language Use | D79: multichoice | G79: SIN CLASIFICAR | H79: Sin coincidencia | I79: Context Elena has demonstrated a remarkable natural talent for numbers and quantitative reasoning from a young age. She is extremely good __
A80: UoL-A2-P02 | B80: A2 | C80: Language Use | D80: multichoice | G80: SIN CLASIFICAR | H80: Sin coincidencia | I80: Context Before choosing a degree programme, Miguel spent months exploring different professional possibilities. He had always been deeply in
A81: UoL-A2-P03 | B81: A2 | C81: Language Use | D81: multichoice | G81: SIN CLASIFICAR | H81: Sin coincidencia | I81: Context Public speaking consistently ranks as one of the most common fears among university students worldwide. Many students admitted that
A82: UoL-A2-P04 | B82: A2 | C82: Language Use | D82: multichoice | G82: SIN CLASIFICAR | H82: Sin coincidencia | I82: Context The student studied at two different institutions before she transferred to her current university. She said the approach to teachin
A83: UoL-A2-P05 | B83: A2 | C83: Language Use | D83: multichoice | G83: SIN CLASIFICAR | H83: Sin coincidencia | I83: Context The student union conducted a survey to find out what activities students most wanted to get involved in. The majority of first-year
A84: UoL-A2-P06 | B84: A2 | C84: Language Use | D84: multichoice | G84: SIN CLASIFICAR | H84: Sin coincidencia | I84: Context The graduation ceremony was a highly emotional occasion for the families of all the new graduates. Every parent in the audience said
A85: UoL-A2-P07 | B85: A2 | C85: Language Use | D85: multichoice | G85: SIN CLASIFICAR | H85: Sin coincidencia | I85: Context The examination results have been taking much longer than expected to appear on the online portal. Several students are extremely wo
A86: UoL-A2-P08 | B86: A2 | C86: Language Use | D86: multichoice | F86: 14 | G86: Making Excuses | H86: Baja (revisar) | I86: Context The student spent an hour comparing two different course structures before making her final decision. She concluded that the content
A87: UoL-A2-P09 | B87: A2 | C87: Language Use | D87: multichoice | F87: 9 | G87: A Bad Day | H87: Baja (revisar) | I87: Context Not all students feel equally confident or competent in every subject they encounter at university. Rodrigo freely admits that he is
A88: UoL-A2-P10 | B88: A2 | C88: Language Use | D88: multichoice | G88: SIN CLASIFICAR | H88: Sin coincidencia | I88: Context The student spent two weeks working on an essay, but then the submission system crashed. She was understandably very angry _____ los
A89: UoL-A2-V01 | B89: A2 | C89: Language Use | D89: multichoice | G89: SIN CLASIFICAR | H89: Sin coincidencia | I89: Context Camila waited anxiously for weeks to hear back from the national scholarship committee. She was absolutely _____ when she finally re
A90: UoL-A2-V02 | B90: A2 | C90: Language Use | D90: multichoice | F90: 13 | G90: Saving Energy | H90: Baja (revisar) | I90: Context Andrés has been saving money for several months to buy the equipment he needs for his studies. Unfortunately, the laptop model he wa
A91: UoL-A2-V03 | B91: A2 | C91: Language Use | D91: multichoice | F91: 8 | G91: Getting Help | H91: Baja (revisar) | I91: Context After six consecutive hours of studying at the library, Ricardo was beginning to feel very unwell. He had a terrible _____ that was
A92: UoL-A2-V04 | B92: A2 | C92: Language Use | D92: multichoice | G92: SIN CLASIFICAR | H92: Sin coincidencia | I92: Context The academic conference included presentations from researchers across many different disciplines. The final speaker was extremely _
A93: UoL-A2-V05 | B93: A2 | C93: Language Use | D93: multichoice | G93: SIN CLASIFICAR | H93: Sin coincidencia | I93: Context The career fair gave students direct access to professionals working in their field of study. Most students said it was extremely __
A94: UoL-A2-V06 | B94: A2 | C94: Language Use | D94: multichoice | F94: 3 | G94: Interesting People | H94: Baja (revisar) | I94: Context Sofia has always maintained a warm and friendly relationship with the people who live near her. Her _____ is a kind elderly woman wh
A95: UoL-A2-V07 | B95: A2 | C95: Language Use | D95: multichoice | G95: SIN CLASIFICAR | H95: Sin coincidencia | I95: Context The new student accommodation was specifically designed with student wellbeing in mind. The rooms are spacious and very _____. Each
A96: UoL-A2-V08 | B96: A2 | C96: Language Use | D96: multichoice | G96: SIN CLASIFICAR | H96: Sin coincidencia | I96: Context Before choosing a university programme, it is essential to research all available options carefully. The admissions office provides
A97: UoL-A2-V09 | B97: A2 | C97: Language Use | D97: multichoice | F97: 7 | G97: Sports | H97: Media (estructura de oracion) | I97: Context The student union organises events throughout the year to bring the university community together. The annual end-of-year celebratio
A98: UoL-A2-V10 | B98: A2 | C98: Language Use | D98: multichoice | F98: 7 | G98: Sports | H98: Media (estructura de oracion) | I98: Context The professor handed back the corrected essays and reviewed the most common errors with the group. She pointed out that the most fre
A99: UoL-A2-V11 | B99: A2 | C99: Language Use | D99: multichoice | G99: SIN CLASIFICAR | H99: Sin coincidencia | I99: Context The university recently invested a significant amount of money in upgrading its facilities. The new engineering laboratories are equ
A100: UoL-A2-V12 | B100: A2 | C100: Language Use | D100: multichoice | G100: SIN CLASIFICAR | H100: Sin coincidencia | I100: Context Students in the first year receive a timetable at the beginning of each semester. It is important to follow your _____ carefully so
...
